models/__init__.py
nhlapi_tools-0.1.2.dist-info/licenses/LICENSE
stats/__init__.py
stats/base.py
stats/draft.py
stats/game.py
stats/misc_stats.py
stats/players.py
stats/season.py
stats/teams.py
web/__init__.py
web/base.py
web/draft.py
web/game.py
web/misc.py
web/other_web.py
web/players.py
web/playoff.py
web/schedule.py
web/teams.py
nhlapi_tools-0.1.2.dist-info/METADATA
nhlapi_tools-0.1.2.dist-info/WHEEL
nhlapi_tools-0.1.2.dist-info/top_level.txt
nhlapi_tools-0.1.2.dist-info/RECORD
