Metadata-Version: 2.4
Name: nhlapi-tools
Version: 0.1.2
Summary: An asynchronous Python wrapper for the official (but undocumented) NHL APIs.
Author-email: Brainey <brrainey13@gmail.com>
License: MIT License
Project-URL: Homepage, https://github.com/brrainey13/nhl-api
Project-URL: Bug Tracker, https://github.com/brrainey13/nhl-api/issues
Project-URL: Documentation, https://github.com/brrainey13/nhl-api/blob/main/nhl_api.md
Classifier: Development Status :: 4 - Beta
Classifier: Programming Language :: Python :: 3
Classifier: Programming Language :: Python :: 3.8
Classifier: Programming Language :: Python :: 3.9
Classifier: Programming Language :: Python :: 3.10
Classifier: Programming Language :: Python :: 3.11
Classifier: Programming Language :: Python :: 3.12
Classifier: License :: OSI Approved :: MIT License
Classifier: Operating System :: OS Independent
Classifier: Intended Audience :: Developers
Classifier: Topic :: Software Development :: Libraries :: Python Modules
Classifier: Framework :: AsyncIO
Classifier: Typing :: Typed
Requires-Python: >=3.8
License-File: LICENSE
Requires-Dist: httpx>=0.24.0
Dynamic: license-file
